itca/__init__.py
itca/metrics.py
itca/search.py
itca/simulation_suites.py
itca/simulator.py
itca/utils.py
itca/visualize.py
itca/datasets/__init__.py
itca/datasets/hydra.npz
itca-0.1.4.dist-info/LICENSE
itca-0.1.4.dist-info/METADATA
itca-0.1.4.dist-info/WHEEL
itca-0.1.4.dist-info/top_level.txt
itca-0.1.4.dist-info/RECORD
