Metadata-Version: 2.1
Name: itca
Version: 0.1.4
Summary: A  Data-driven Criterion to Combining Ambiguous Outcome Labels in Multi-class Classification
Home-page: https://github.com/JSB-UCLA/ITCA
Author: Chihao Zhang
Author-email: zhang.dabiao11@gmail.com
License: MIT
Classifier: License :: OSI Approved :: MIT License
Classifier: Programming Language :: Python
Classifier: Programming Language :: Python :: 3
Classifier: Programming Language :: Python :: 3.6
Classifier: Programming Language :: Python :: Implementation :: CPython
Classifier: Programming Language :: Python :: Implementation :: PyPy
Requires-Python: >=3.6.0
License-File: LICENSE
Requires-Dist: numpy
Requires-Dist: scikit-learn
Requires-Dist: networkx
Requires-Dist: matplotlib
Requires-Dist: pydot
Provides-Extra: pygraphviz
Requires-Dist: pygraphviz ; extra == 'pygraphviz'
